btrfcomm/__init__.py
btrfcomm/__main__.py
btrfcomm/client.py
btrfcomm/helper.py
btrfcomm/rfcomm.py
btrfcomm/server.py
btrfcomm/pytransform/__init__.py
btrfcomm/pytransform/platforms/linux/aarch64/_pytransform.so
btrfcomm/pytransform/platforms/linux/x86_64/_pytransform.so
btrfcomm-0.0.3.dist-info/LICENSE.txt
btrfcomm-0.0.3.dist-info/METADATA
btrfcomm-0.0.3.dist-info/WHEEL
btrfcomm-0.0.3.dist-info/top_level.txt
btrfcomm-0.0.3.dist-info/RECORD
